geneweaver/client/__init__.py
geneweaver/client/api/__init__.py
geneweaver/client/api/aon.py
geneweaver/client/api/exc.py
geneweaver/client/api/genes.py
geneweaver/client/api/genesets.py
geneweaver/client/api/graph.py
geneweaver/client/api/mapping.py
geneweaver/client/api/utils.py
geneweaver/client/auth.py
geneweaver/client/batch/__init__.py
geneweaver/client/cli/__init__.py
geneweaver/client/cli/alpha/__init__.py
geneweaver/client/cli/alpha/api/__init__.py
geneweaver/client/cli/alpha/api/genes.py
geneweaver/client/cli/alpha/api/genesets.py
geneweaver/client/cli/alpha/api/list.py
geneweaver/client/cli/alpha/datasets/__init__.py
geneweaver/client/cli/alpha/datasets/main.py
geneweaver/client/cli/alpha/geneset.py
geneweaver/client/cli/alpha/parse/__init__.py
geneweaver/client/cli/alpha/parse/batch.py
geneweaver/client/cli/alpha/parse/convert.py
geneweaver/client/cli/alpha/parse/main.py
geneweaver/client/cli/alpha/parse/utils.py
geneweaver/client/cli/beta/__init__.py
geneweaver/client/cli/beta/auth.py
geneweaver/client/cli/main.py
geneweaver/client/core/__init__.py
geneweaver/client/core/app_dir.py
geneweaver/client/core/config.py
geneweaver/client/core/config_class.py
geneweaver/client/datasets/__init__.py
geneweaver/client/datasets/base.py
geneweaver/client/datasets/nci60/__init__.py
geneweaver/client/datasets/nci60/dna_combined_acgh_gene_summary.py
geneweaver/client/exceptions.py
geneweaver/client/gedb.py
geneweaver/client/parser/__init__.py
geneweaver/client/parser/batch.py
geneweaver/client/parser/general.py
geneweaver/client/render/__init__.py
geneweaver/client/user_config.py
geneweaver/client/utils/__init__.py
geneweaver/client/utils/aon.py
geneweaver/client/utils/cli/__init__.py
geneweaver/client/utils/cli/decorators/__init__.py
geneweaver/client/utils/cli/decorators/errors.py
geneweaver/client/utils/cli/decorators/options.py
geneweaver/client/utils/cli/print/__init__.py
geneweaver/client/utils/cli/print/csv.py
geneweaver/client/utils/cli/print/file_info.py
geneweaver_client-0.10.0.dist-info/LICENSE
geneweaver_client-0.10.0.dist-info/METADATA
geneweaver_client-0.10.0.dist-info/WHEEL
geneweaver_client-0.10.0.dist-info/entry_points.txt
geneweaver_client-0.10.0.dist-info/RECORD
