Metadata-Version: 2.1
Name: geneweaver-client
Version: 0.10.0
Summary: A Python Client for the Geneweaver API
Home-page: https://thejacksonlaboratory.github.io/geneweaver-docs/
License: Apache-2.0
Author: Jax Computational Sciences
Author-email: cssc@jax.org
Requires-Python: >=3.9,<4.0
Classifier: License :: OSI Approved :: Apache Software License
Classifier: Programming Language :: Python :: 3
Classifier: Programming Language :: Python :: 3.9
Classifier: Programming Language :: Python :: 3.10
Classifier: Programming Language :: Python :: 3.11
Classifier: Programming Language :: Python :: 3.12
Requires-Dist: auth0-python (>=4.7,<5.0)
Requires-Dist: geneweaver-core (>=0.10.0a3,<0.11.0)
Requires-Dist: openpyxl (>=3.1,<4.0)
Requires-Dist: pandas (>=1.5,<3)
Requires-Dist: pydantic-settings (>=2.4.0,<3.0.0)
Requires-Dist: pydantic[dotenv] (>=2,<3)
Requires-Dist: requests (>=2.28,<3.0)
Requires-Dist: rich (>=13.7,<14.0)
Requires-Dist: typer[all] (>=0.12,<0.13)
Requires-Dist: xlrd (>=2.0,<3.0)
Project-URL: Repository, https://github.com/TheJacksonLaboratory/geneweaver-client
